unlearn3d/__init__.py
unlearn3d-0.0.0.dist-info/METADATA
unlearn3d-0.0.0.dist-info/WHEEL
unlearn3d-0.0.0.dist-info/top_level.txt
unlearn3d-0.0.0.dist-info/RECORD
