Metadata-Version: 2.1
Name: unlearn3d
Version: 0.0.0
Summary: Coming soon
Author-email: Kyle Fogarty <ktf25@cam.ac.uk>
